amtFMC/FMC_funct.py
amtFMC/__init__.py
amtFMC/debug_funct.py
amtFMC/examples/labview_examples/firmware_version.vi
amtFMC/examples/labview_examples/initialize.vi
amtFMC/examples/labview_examples/receive.vi
amtFMC/examples/labview_examples/transceive.vi
amtFMC/examples/labview_examples/transmit.vi
amtFMC/examples/python_examples/change_ref_clk.py
amtFMC/examples/python_examples/firmware.py
amtFMC/examples/python_examples/initialize.py
amtFMC/examples/python_examples/receive.py
amtFMC/examples/python_examples/transceive.py
amtFMC/examples/python_examples/transmit.py
amtFMC-0.0.3.dist-info/LICENSE.txt
amtFMC-0.0.3.dist-info/METADATA
amtFMC-0.0.3.dist-info/WHEEL
amtFMC-0.0.3.dist-info/entry_points.txt
amtFMC-0.0.3.dist-info/top_level.txt
amtFMC-0.0.3.dist-info/RECORD
